halo_server_query/__init__.py
halo_server_query/halo_server_query.py
HaloServerQuery-1.0.1.dist-info/LICENSE
HaloServerQuery-1.0.1.dist-info/METADATA
HaloServerQuery-1.0.1.dist-info/WHEEL
HaloServerQuery-1.0.1.dist-info/top_level.txt
HaloServerQuery-1.0.1.dist-info/RECORD
