Metadata-Version: 2.1
Name: HaloServerQuery
Version: 1.0.1
Summary: Query Halo Custom Edition servers for valuable information
Home-page: https://github.com/TagiaNetwork/Halo-Server-Query
Author: Tagia Network
Author-email: tagianetwork@gmail.com
Project-URL: Bug Tracker, https://github.com/TagiaNetwork/Halo-Server-Query/issues
Classifier: Programming Language :: Python :: 3
Classifier: License :: OSI Approved :: MIT License
Classifier: Operating System :: OS Independent
Requires-Python: >=3.6
License-File: LICENSE
